{
  "/anime/plus-sized-misadventures-in-love/": {
    "group": "PLUS-SIZED MISADVENTURES IN LOVE!",
    "last_season": 1,
    "last_episode": 1,
    "start_episode": 1
  },
  "/anime/a-mangakas-weirdly-wonderful-workplace/": {
    "group": "A MANGAKA’S WEIRDLY WONDERFUL WORKPLACE",
    "last_season": 1,
    "last_episode": 1,
    "start_episode": 1
  },
  "/anime/hands-off-sawaranaide-kotesashi-kun-uncensored/": {
    "group": "HANDS OFF: SAWARANAIDE KOTESASHI-KUN (UNCENSORED)",
    "last_season": 1,
    "last_episode": 2,
    "start_episode": 1
  },
  "/anime/the-fated-magical-princess-who-made-me-a-princess/": {
    "group": "THE FATED MAGICAL PRINCESS: WHO MADE ME A PRINCESS",
    "last_season": 1,
    "last_episode": 5,
    "start_episode": 1
  },
  "/anime/one-piece/": {
    "group": "ONE PIECE",
    "last_season": 1,
    "last_episode": 1145,
    "start_episode": 1130
  },
  "/anime/one-punch-man-season-3/": {
    "group": "ONE-PUNCH MAN SEASON 3",
    "last_season": 1,
    "last_episode": 1,
    "start_episode": 1
  },
  "/anime/gachiakuta/": {
    "group": "GACHIAKUTA",
    "last_season": 1,
    "last_episode": 14,
    "start_episode": 1
  },
  "/anime/dad-is-a-hero-mom-is-a-spirit-im-a-reincarnator/": {
    "group": "DAD IS A HERO, MOM IS A SPIRIT, I’M A REINCARNATOR",
    "last_season": 1,
    "last_episode": 2,
    "start_episode": 1
  },
  "/anime/alma-chan-wants-to-be-a-family/": {
    "group": "ALMA-CHAN WANTS TO BE A FAMILY!",
    "last_season": 1,
    "last_episode": 2,
    "start_episode": 1
  },
  "/anime/mechanical-marie/": {
    "group": "MECHANICAL MARIE",
    "last_season": 1,
    "last_episode": 2,
    "start_episode": 1
  },
  "/anime/lil-miss-vampire-cant-suck-right/": {
    "group": "LI’L MISS VAMPIRE CAN’T SUCK RIGHT",
    "last_season": 1,
    "last_episode": 1,
    "start_episode": 1
  },
  "/anime/blue-orchestra-season-2/": {
    "group": "BLUE ORCHESTRA SEASON 2",
    "last_season": 1,
    "last_episode": 2,
    "start_episode": 1
  },
  "/anime/umamusume-cinderella-gray-part-2/": {
    "group": "UMAMUSUME: CINDERELLA GRAY PART 2",
    "last_season": 1,
    "last_episode": 2,
    "start_episode": 1
  },
  "/anime/digimon-beatbreak/": {
    "group": "DIGIMON BEATBREAK",
    "last_season": 1,
    "last_episode": 2,
    "start_episode": 1
  },
  "/anime/kingdom-season-6/": {
    "group": "KINGDOM: SEASON 6",
    "last_season": 1,
    "last_episode": 2,
    "start_episode": 1
  },
  "/anime/my-friends-little-sister-has-it-in-for-me/": {
    "group": "MY FRIEND’S LITTLE SISTER HAS IT IN FOR ME!",
    "last_season": 1,
    "last_episode": 2,
    "start_episode": 1
  },
  "/anime/ranma-%c2%bd-2024-2nd-season/": {
    "group": "RANMA ½ (2024) 2ND SEASON",
    "last_season": 1,
    "last_episode": 2,
    "start_episode": 1
  },
  "/anime/tojima-wants-to-be-a-kamen-rider/": {
    "group": "TOJIMA WANTS TO BE A KAMEN RIDER",
    "last_season": 1,
    "last_episode": 2,
    "start_episode": 1
  },
  "/anime/gnosia/": {
    "group": "GNOSIA",
    "last_season": 1,
    "last_episode": 1,
    "start_episode": 1
  },
  "/anime/touring-after-the-apocalypse/": {
    "group": "TOURING AFTER THE APOCALYPSE",
    "last_season": 1,
    "last_episode": 2,
    "start_episode": 1
  }
}